signaturizer3d/__init__.py
signaturizer3d/inference.py
signaturizer3d/input/__init__.py
signaturizer3d/input/sdf.py
signaturizer3d/input/smiles.py
signaturizer3d/input/unimol_adapter.py
signaturizer3d/model.py
signaturizer3d/normalize/normalize.py
signaturizer3d/normalize/space_means.pkl
signaturizer3d/normalize/space_stds.pkl
signaturizer3d/signaturizer.py
signaturizer3d/space.py
signaturizer3d/unicore/LICENSE
signaturizer3d/unicore/__init__.py
signaturizer3d/unicore/dictionary.py
signaturizer3d/unicore/layer_norm.py
signaturizer3d/unicore/multihead_attention.py
signaturizer3d/unicore/softmax_dropout.py
signaturizer3d/unicore/transformer_encoder.py
signaturizer3d/unicore/transformer_encoder_layer.py
signaturizer3d/unicore/unicore_model.py
signaturizer3d/unicore/utils.py
signaturizer3d/unimol/LICENSE
signaturizer3d/unimol/__init__.py
signaturizer3d/unimol/dict.txt
signaturizer3d/unimol/pad.py
signaturizer3d/unimol/transformers.py
signaturizer3d/unimol/unimol.py
signaturizer3d-0.1.8.dist-info/LICENSE
signaturizer3d-0.1.8.dist-info/METADATA
signaturizer3d-0.1.8.dist-info/WHEEL
signaturizer3d-0.1.8.dist-info/RECORD
