Metadata-Version: 2.1
Name: signaturizer3D
Version: 0.1.8
Summary: Infer the bioactivity of molecules using models trained on molecular 3D structures.
Home-page: https://gitlabsbnb.irbbarcelona.org/alenes/signaturizer3d
License: MIT
Author: Aksel Lenes
Author-email: aksel.lenes@irbbarcelona.org
Requires-Python: >=3.9,<3.13
Classifier: License :: OSI Approved :: MIT License
Classifier: Programming Language :: Python :: 3
Classifier: Programming Language :: Python :: 3.9
Classifier: Programming Language :: Python :: 3.10
Classifier: Programming Language :: Python :: 3.11
Classifier: Programming Language :: Python :: 3.12
Requires-Dist: addict (>=2.0.0,<3.0.0)
Requires-Dist: chardet (>=5.2.0,<6.0.0)
Requires-Dist: numpy (>=1.0.0,<2.0.0)
Requires-Dist: pandas (>=2.0.0,<3.0.0)
Requires-Dist: rdkit-pypi (>=2022.9.3,<2023.0.0)
Requires-Dist: tqdm (>=4.0.0,<5.0.0)
Project-URL: Repository, https://gitlabsbnb.irbbarcelona.org/alenes/signaturizer3d
